LICENSE
MANIFEST.in
README.rst
VERSION
requirements.txt
setup.py
src/kser_transport_http/__init__.py
src/kser_transport_http/consumer.py
src/kser_transport_http/producer.py
src/kser_transport_http.egg-info/PKG-INFO
src/kser_transport_http.egg-info/SOURCES.txt
src/kser_transport_http.egg-info/dependency_links.txt
src/kser_transport_http.egg-info/entry_points.txt
src/kser_transport_http.egg-info/requires.txt
src/kser_transport_http.egg-info/top_level.txt
src/kser_transport_http.egg-info/zip-safe